chamgo/__init__.py
chamgo/__main__.py
chamgo/chamgo.py
chamgo-0.1.8.dist-info/LICENSE
chamgo-0.1.8.dist-info/METADATA
chamgo-0.1.8.dist-info/WHEEL
chamgo-0.1.8.dist-info/entry_points.txt
chamgo-0.1.8.dist-info/top_level.txt
chamgo-0.1.8.dist-info/RECORD
