Metadata-Version: 2.1
Name: chamgo
Version: 0.1.8
Summary: Get LLM to review your commit
Requires-Python: >=3.13
License-File: LICENSE
Requires-Dist: langchain-openai>=0.2.9
Requires-Dist: python-dotenv>=1.0.1
Requires-Dist: rich>=13.9.4
